isaf/__init__.py
isaf/cli.py
isaf/config.py
isaf/decorators.py
isaf/core/__init__.py
isaf/core/extractors.py
isaf/core/session.py
isaf/export/__init__.py
isaf/export/exporter.py
isaf/storage/__init__.py
isaf/storage/base.py
isaf/storage/mlflow_backend.py
isaf/storage/sqlite_backend.py
isaf/verification/__init__.py
isaf/verification/hash_chain.py
isaf_logger-0.2.0.dist-info/licenses/LICENSE
isaf_logger-0.2.0.dist-info/METADATA
isaf_logger-0.2.0.dist-info/WHEEL
isaf_logger-0.2.0.dist-info/entry_points.txt
isaf_logger-0.2.0.dist-info/top_level.txt
isaf_logger-0.2.0.dist-info/RECORD
