Metadata-Version: 2.4
Name: isaf-logger
Version: 0.2.0
Summary: Instruction Stack Audit Framework - Automatic compliance logging for AI systems
Home-page: https://github.com/haiec/isaf-logger
Author: HAIEC Lab
Author-email: HAIEC Lab <contact@haiec.com>
License: MIT
Project-URL: Homepage, https://haiec.com/isaf
Project-URL: Documentation, https://haiec.com/isaf/docs
Project-URL: Repository, https://github.com/haiec/isaf-logger
Project-URL: Bug Tracker, https://github.com/haiec/isaf-logger/issues
Keywords: ai,ml,compliance,audit,logging,eu-ai-act,nist,isaf
Classifier: Development Status :: 4 - Beta
Classifier: Intended Audience :: Developers
Classifier: Intended Audience :: Science/Research
Classifier: License :: OSI Approved :: MIT License
Classifier: Operating System :: OS Independent
Classifier: Programming Language :: Python :: 3
Classifier: Programming Language :: Python :: 3.8
Classifier: Programming Language :: Python :: 3.9
Classifier: Programming Language :: Python :: 3.10
Classifier: Programming Language :: Python :: 3.11
Classifier: Programming Language :: Python :: 3.12
Classifier: Topic :: Scientific/Engineering :: Artificial Intelligence
Requires-Python: >=3.8
License-File: LICENSE
Requires-Dist: click>=8.0.0
Provides-Extra: numpy
Requires-Dist: numpy>=1.19.0; extra == "numpy"
Provides-Extra: mlflow
Requires-Dist: mlflow>=2.0.0; extra == "mlflow"
Provides-Extra: all
Requires-Dist: numpy>=1.19.0; extra == "all"
Requires-Dist: mlflow>=2.0.0; extra == "all"
Provides-Extra: dev
Requires-Dist: pytest>=7.0.0; extra == "dev"
Requires-Dist: pytest-cov>=3.0.0; extra == "dev"
Requires-Dist: black>=22.0.0; extra == "dev"
Requires-Dist: flake8>=4.0.0; extra == "dev"
Requires-Dist: mlflow>=2.0.0; extra == "dev"
Requires-Dist: numpy>=1.19.0; extra == "dev"
Dynamic: author
Dynamic: home-page
Dynamic: license-file
Dynamic: requires-python
